[{"Alcohol Type":"Vodka","Brand":"Absolut 1L","Price":11.0},{"Alcohol Type":"Vodka","Brand":"Absolut Mandarin 1L","Price":11.0},{"Alcohol Type":"Vodka","Brand":"Absolut Rasberi","Price":11.0},{"Alcohol Type":"Vodka","Brand":"Absolut Vanilla","Price":11.0},{"Alcohol Type":"Vodka","Brand":"Belvedere 1L","Price":15.5},{"Alcohol Type":"Vodka","Brand":"Chopin","Price":15.5},{"Alcohol Type":"Vodka","Brand":"Ciroc 1L","Price":15.5},{"Alcohol Type":"Vodka","Brand":"Grey Goose 1L","Price":15.5},{"Alcohol Type":"Vodka","Brand":"HDW Clix Vodka","Price":50.0},{"Alcohol Type":"Vodka","Brand":"High Bank Vodka 1L","Price":12.5},{"Alcohol Type":"Vodka","Brand":"Ketel One 1L","Price":14.5},{"Alcohol Type":"Vodka","Brand":"Ketel One Citroen","Price":14.5},{"Alcohol Type":"Vodka","Brand":"Tito's 1L","Price":14.5},{"Alcohol Type":"Vodka","Brand":"wheatley vodka","Price":12.5},{"Alcohol Type":"Vodka","Brand":"Watershed Vodka 1L","Price":13.5},{"Alcohol Type":"Tequila","Brand":"Cantera Negra Anejo","Price":21.5},{"Alcohol Type":"Tequila","Brand":"Cantera Negra Extra Anejo","Price":27.5},{"Alcohol Type":"Tequila","Brand":"Cantera Negra Reposado","Price":18.5},{"Alcohol Type":"Tequila","Brand":"Cantera Negra Silver","Price":16.5},{"Alcohol Type":"Tequila","Brand":"Casamigos Anejo","Price":18.5},{"Alcohol Type":"Tequila","Brand":"Casamigos Blanco","Price":15.5},{"Alcohol Type":"Tequila","Brand":"Casamigos Reposado","Price":16.5},{"Alcohol Type":"Tequila","Brand":"Cincoro Anejo","Price":33.5},{"Alcohol Type":"Tequila","Brand":"Cincoro Blanco","Price":23.5},{"Alcohol Type":"Tequila","Brand":"Cincoro Extra Anejo","Price":252.5},{"Alcohol Type":"Tequila","Brand":"Cincoro Reposado","Price":27.5},{"Alcohol Type":"Tequila","Brand":"Clase Azul Plata","Price":32.5},{"Alcohol Type":"Tequila","Brand":"Clase Azul Reposado","Price":34.5},{"Alcohol Type":"Tequila","Brand":"Corazon Expresiones George T. Stagg anejo","Price":42.5},{"Alcohol Type":"Tequila","Brand":"Don Julio 1942","Price":37.5},{"Alcohol Type":"Tequila","Brand":"Don Julio 70th","Price":23.5},{"Alcohol Type":"Tequila","Brand":"Espolon Silver","Price":11.0},{"Alcohol Type":"Tequila","Brand":"Gran Patron 'Piedre'","Price":72.5},{"Alcohol Type":"Tequila","Brand":"Hornitos Plata ","Price":11.0},{"Alcohol Type":"Tequila","Brand":"Patron Anejo","Price":17.5},{"Alcohol Type":"Tequila","Brand":"Patron Reposado","Price":16.5},{"Alcohol Type":"Tequila","Brand":"Patron Silver","Price":15.5},{"Alcohol Type":"Tequila","Brand":"Rey Sol 6yr Extra Anejo","Price":55.0},{"Alcohol Type":"Tequila","Brand":"Tres Generaciones Plata","Price":13.0},{"Alcohol Type":"Bourbon","Brand":"Angel's Envy","Price":16.5},{"Alcohol Type":"Bourbon","Brand":"Baker's Single Barrel","Price":18.5},{"Alcohol Type":"Bourbon","Brand":"Bardstown Discovery Series","Price":33.5},{"Alcohol Type":"Bourbon","Brand":"Basil Hayden","Price":15.5},{"Alcohol Type":"Bourbon","Brand":"Basil Hayden Subtle Smoke","Price":17.5},{"Alcohol Type":"Bourbon","Brand":"Basil Hayden Red Wine Cask","Price":18.5},{"Alcohol Type":"Bourbon","Brand":"Basil Hayden Toasted Oak","Price":17.5},{"Alcohol Type":"Bourbon","Brand":"Blade & Bow","Price":17.5},{"Alcohol Type":"Bourbon","Brand":"Blanton's","Price":27.5},{"Alcohol Type":"Bourbon","Brand":"Blood Oath Pact No. 8","Price":29.5},{"Alcohol Type":"Bourbon","Brand":"Booker's","Price":26.5},{"Alcohol Type":"Bourbon","Brand":"Buffalo Trace","Price":15.5},{"Alcohol Type":"Bourbon","Brand":"Bulleit","Price":11.75},{"Alcohol Type":"Bourbon","Brand":"Bulleit 1L","Price":11.0},{"Alcohol Type":"Bourbon","Brand":"Bulleit 10","Price":15.5},{"Alcohol Type":"Bourbon","Brand":"Calumet Farm 16 - Citation","Price":40.0},{"Alcohol Type":"Bourbon","Brand":"Calumet Farm 15 - Whirlaway","Price":35.0},{"Alcohol Type":"Bourbon","Brand":"Calumet Farm 10","Price":36.0},{"Alcohol Type":"Bourbon","Brand":"Chicken Cock Bourbon","Price":24.0},{"Alcohol Type":"Bourbon","Brand":"Courage and Conviction Cask Strength Bourbon","Price":32.0},{"Alcohol Type":"Bourbon","Brand":"Eagle Rare","Price":15.5},{"Alcohol Type":"Bourbon","Brand":"EH Taylor Sm Batch","Price":19.0},{"Alcohol Type":"Bourbon","Brand":"Elijah Craig 18yr","Price":37.5},{"Alcohol Type":"Bourbon","Brand":"Elijah Craig Small Batch","Price":24.5},{"Alcohol Type":"Bourbon","Brand":"Elijah Craig Barrel Proof","Price":20.5},{"Alcohol Type":"Bourbon","Brand":"Elijah Craig Toasted Barrel","Price":17.5},{"Alcohol Type":"Bourbon","Brand":"Four Roses Single Barrel","Price":18.0},{"Alcohol Type":"Bourbon","Brand":"Four Roses Small Batch","Price":16.0},{"Alcohol Type":"Bourbon","Brand":"Four Roses Sm Batch 90","Price":18.0},{"Alcohol Type":"Bourbon","Brand":"Four Roses Sm Batch SELECT","Price":22.0},{"Alcohol Type":"Bourbon","Brand":"George Dickel Barrel Select","Price":18.0},{"Alcohol Type":"Bourbon","Brand":"George Remus Bourbon","Price":15.5},{"Alcohol Type":"Bourbon","Brand":"Hayner Bourbon","Price":18.5},{"Alcohol Type":"Bourbon","Brand":"Heaven's Door TN Bourbon","Price":21.5},{"Alcohol Type":"Bourbon","Brand":"Heaven Hill Bottled In Bond","Price":22.5},{"Alcohol Type":"Bourbon","Brand":"Henry McKenna Bottled In Bond","Price":18.5},{"Alcohol Type":"Bourbon","Brand":"High Bank Whiskey War","Price":13.5},{"Alcohol Type":"Bourbon","Brand":"High Bank Whiskey War Barrel Proof","Price":16.5},{"Alcohol Type":"Bourbon","Brand":"High Bank Whiskey War Double Oaked","Price":30.0},{"Alcohol Type":"Bourbon","Brand":"Horse Soldier Barrel Strength","Price":22.5},{"Alcohol Type":"Bourbon","Brand":"Horse Soldier Small Batch","Price":20.5},{"Alcohol Type":"Bourbon","Brand":"IW Harper Cabernet Cask Bourbon","Price":21.5},{"Alcohol Type":"Bourbon","Brand":"Jefferson's Ocean Voyage 25","Price":22.5},{"Alcohol Type":"Bourbon","Brand":"Jefferson's Reserve Old Rum Cask","Price":20.5},{"Alcohol Type":"Bourbon","Brand":"Jefferson's Reserve Single Barrel","Price":17.5},{"Alcohol Type":"Bourbon","Brand":"Jefferson's Reserve Twin Oak Barrel","Price":20.5},{"Alcohol Type":"Bourbon","Brand":"Joseph Magnus Cigar Blend","Price":55.0},{"Alcohol Type":"Bourbon","Brand":"Joseph Magnus ","Price":55.0},{"Alcohol Type":"Bourbon","Brand":"Kentucky Owl Confiscated","Price":32.5},{"Alcohol Type":"Bourbon","Brand":"Kentucky Owl St. Paddy's Bourbon","Price":35.0},{"Alcohol Type":"Bourbon","Brand":"Knob Creek","Price":13.0},{"Alcohol Type":"Bourbon","Brand":"Knob Creek 12 Year","Price":40.0},{"Alcohol Type":"Bourbon","Brand":"Knob Creek 18 Year","Price":55.0},{"Alcohol Type":"Bourbon","Brand":"Larceny Barrel Proof","Price":18.5},{"Alcohol Type":"Bourbon","Brand":"Little Book 6 - To the Finish","Price":40.0},{"Alcohol Type":"Bourbon","Brand":"Maker's Mark","Price":12.5},{"Alcohol Type":"Bourbon","Brand":"Maker's Mark 101","Price":17.0},{"Alcohol Type":"Bourbon","Brand":"Michter's Small Batch Bbn","Price":16.5},{"Alcohol Type":"Bourbon","Brand":"Middle West Sherry Finish","Price":27.5},{"Alcohol Type":"Bourbon","Brand":"Murray Hill Club Bourbon","Price":32.5},{"Alcohol Type":"Bourbon","Brand":"Nelson Bros. Reserve Bourbon","Price":20.5},{"Alcohol Type":"Bourbon","Brand":"Noah's Mill Bourbon","Price":18.5},{"Alcohol Type":"Bourbon","Brand":"Old Elk Armagnac Cask","Price":37.5},{"Alcohol Type":"Bourbon","Brand":"Old Forester","Price":11.0},{"Alcohol Type":"Bourbon","Brand":"Old Forester 1920","Price":18.5},{"Alcohol Type":"Bourbon","Brand":"Old Forester Statesman","Price":17.5},{"Alcohol Type":"Bourbon","Brand":"Peerless Barrel Proof","Price":26.5},{"Alcohol Type":"Bourbon","Brand":"Rowan's Creek","Price":17.5},{"Alcohol Type":"Bourbon","Brand":"Smooth Ambler Contradiction","Price":14.5},{"Alcohol Type":"Bourbon","Brand":"Thomas S. Moore Bbn Port Cask","Price":20.5},{"Alcohol Type":"Bourbon","Brand":"Thomas S. Moore Chardonnay Cask","Price":20.5},{"Alcohol Type":"Bourbon","Brand":"Watershed Bottled in Bond","Price":16.5},{"Alcohol Type":"Bourbon","Brand":"Watershed 4yr Bourbon","Price":15.0},{"Alcohol Type":"Bourbon","Brand":"Watershed Barrel Proof Bbn Private Barrel","Price":18.5},{"Alcohol Type":"Bourbon","Brand":"Weller 12yr","Price":18.5},{"Alcohol Type":"Bourbon","Brand":"Weller Antique","Price":17.5},{"Alcohol Type":"Bourbon","Brand":"Weller Special Reserve","Price":12.5},{"Alcohol Type":"Bourbon","Brand":"Wilderness Trail Small Batch Rye BIB","Price":17.5},{"Alcohol Type":"Bourbon","Brand":"Wild Turkey Kentucky Spirit","Price":18.5},{"Alcohol Type":"Bourbon","Brand":"Wild Turkey Kentucky Spirit Single Barrel","Price":19.5},{"Alcohol Type":"Bourbon","Brand":"Wild Turkey Long Branch","Price":12.5},{"Alcohol Type":"Bourbon","Brand":"Willett Pot Still Reserve (1.5L)","Price":27.5},{"Alcohol Type":"Bourbon","Brand":"Willett 8 Year Wheated","Price":28.5},{"Alcohol Type":"Bourbon","Brand":"Wiseman Bourbon","Price":17.5},{"Alcohol Type":"Bourbon","Brand":"Woodford Reserve 1L","Price":13.0},{"Alcohol Type":"Bourbon","Brand":"Woodford Reserve Double Oaked","Price":16.5},{"Alcohol Type":"Bourbon","Brand":"Woodford Reserve Masters Collection","Price":33.5},{"Alcohol Type":"Bourbon","Brand":"Woodford Reserve Straight Wheat","Price":15.5},{"Alcohol Type":"Bourbon","Brand":" Woodinville Private Select","Price":16.5},{"Alcohol Type":"Bourbon","Brand":"Yellowstone Handpicked Barrel Proof","Price":18.5},{"Alcohol Type":"Bourbon","Brand":"Yellowstone Handpicked Single Barrel 2022","Price":19.5},{"Alcohol Type":"Bourbon","Brand":"Yellowstone Select Single Barrel","Price":16.5},{"Alcohol Type":"Gin","Brand":"Beefeater","Price":11.0},{"Alcohol Type":"Gin","Brand":"Bombay Dry 1L","Price":11.0},{"Alcohol Type":"Gin","Brand":"Bombay Sapphire","Price":11.75},{"Alcohol Type":"Gin","Brand":"Botanist","Price":14.5},{"Alcohol Type":"Gin","Brand":"Echo Spirits Genevere","Price":13.0},{"Alcohol Type":"Gin","Brand":"Gray Whale Gin","Price":16.5},{"Alcohol Type":"Gin","Brand":"Hendrick's 1L","Price":13.5},{"Alcohol Type":"Gin","Brand":"Hendrick's Neptunia","Price":14.5},{"Alcohol Type":"Gin","Brand":"High Bank Statehouse Gin","Price":12.5},{"Alcohol Type":"Gin","Brand":"Middle West Vim & Petal","Price":13.5},{"Alcohol Type":"Gin","Brand":"Monkey 47 1L","Price":16.5},{"Alcohol Type":"Gin","Brand":"Nolet's","Price":14.5},{"Alcohol Type":"Gin","Brand":"Roku Gin","Price":13.5},{"Alcohol Type":"Gin","Brand":"Tanqueray","Price":11.75},{"Alcohol Type":"Gin","Brand":"Tanqueray 10","Price":13.0},{"Alcohol Type":"Gin","Brand":"Watershed Bourbon Barrel","Price":14.5},{"Alcohol Type":"Gin","Brand":"Watershed Four Peel ","Price":12.5},{"Alcohol Type":"Gin","Brand":"Watershed Strawberry Four Peel","Price":18.5},{"Alcohol Type":"Gin","Brand":"Watershed Guild","Price":13.5},{"Alcohol Type":"Rum","Brand":"Appleton Signture Blend","Price":11.75},{"Alcohol Type":"Rum","Brand":"Appleton 12 Rare Cask","Price":14.5},{"Alcohol Type":"Rum","Brand":"Bumbu","Price":14.5},{"Alcohol Type":"Rum","Brand":"Captain Morgan 1L","Price":11.0},{"Alcohol Type":"Rum","Brand":"Diplomatico Reserva Exclusiva","Price":15.5},{"Alcohol Type":"Rum","Brand":"Echo Spirits Pineapple Rum","Price":12.5},{"Alcohol Type":"Rum","Brand":"Novo Fugo Cachacha","Price":13.0},{"Alcohol Type":"Rum","Brand":"Myer's Dark Rum 1L","Price":11.0},{"Alcohol Type":"Rum","Brand":"Plantation 3 Stars 1L","Price":11.0},{"Alcohol Type":"Rum","Brand":"Plantation Dark","Price":11.0},{"Alcohol Type":"Rum","Brand":"Plantation OFTD 1L","Price":12.5},{"Alcohol Type":"Rum","Brand":"Plantation Pineapple","Price":11.75},{"Alcohol Type":"Rum","Brand":"Rhum JM Blanc","Price":14.5},{"Alcohol Type":"Scotch","Brand":"Balvenie 12 Double Wood","Price":18.5},{"Alcohol Type":"Scotch","Brand":"Balvenie 14 Caribbean Cask","Price":20.5},{"Alcohol Type":"Scotch","Brand":"Bruichladdich Classic Laddie","Price":22.5},{"Alcohol Type":"Scotch","Brand":"Bruichladdich Port Charlotte","Price":23.5},{"Alcohol Type":"Scotch","Brand":"Chivas Regal 12 1L","Price":12.5},{"Alcohol Type":"Scotch","Brand":"Dewars White 1L","Price":11.5},{"Alcohol Type":"Scotch","Brand":"Glenlivet Founder's Reserve","Price":17.5},{"Alcohol Type":"Scotch","Brand":"Glenlivet 12","Price":15.5},{"Alcohol Type":"Scotch","Brand":"Glenmorangie 18","Price":16.5},{"Alcohol Type":"Scotch","Brand":"Glenmorangie Nectar D'or","Price":17.5},{"Alcohol Type":"Scotch","Brand":"Glenmorangie Tale of the Forest","Price":35.5},{"Alcohol Type":"Scotch","Brand":"Johnnie Walker Black 1L","Price":15.5},{"Alcohol Type":"Scotch","Brand":"Johnnie Walker Blue","Price":42.5},{"Alcohol Type":"Scotch","Brand":"Johnnie Walker Red 1L","Price":11.0},{"Alcohol Type":"Scotch","Brand":"Lagavulin Offerman Edition Oak Cask","Price":29.5},{"Alcohol Type":"Scotch","Brand":"Lagavulin 16","Price":20.5},{"Alcohol Type":"Scotch","Brand":"Laphroiag 10","Price":16.5},{"Alcohol Type":"Scotch","Brand":"Macallan 12 Sherry Cask","Price":19.5},{"Alcohol Type":"Scotch","Brand":"Macallan 12 Double Cask","Price":27.0},{"Alcohol Type":"Scotch","Brand":"Macallan 15 Double Cask","Price":55.0},{"Alcohol Type":"Scotch","Brand":"Macallan 18 Double Cask","Price":125.0},{"Alcohol Type":"Scotch","Brand":"Oban 14","Price":20.5},{"Alcohol Type":"Scotch","Brand":"Oban Little Bay Single Malt","Price":29.5},{"Alcohol Type":"Scotch","Brand":"Redbreast 12","Price":18.5},{"Alcohol Type":"Scotch","Brand":"Redbreast Cask Strength","Price":33.0},{"Alcohol Type":"Scotch","Brand":"The Dalmore Cigar","Price":39.0},{"Alcohol Type":"Scotch","Brand":"The Dalmore 12 Year","Price":27.5},{"Alcohol Type":"Scotch","Brand":"The Dalmore 14 Year","Price":40.0},{"Alcohol Type":"Mezcal","Brand":"Bozal Borrego Mezcal","Price":33.0},{"Alcohol Type":"Mezcal","Brand":"Bozal Castilla Mezcal","Price":35.0},{"Alcohol Type":"Mezcal","Brand":"Bozal Cuishe Mezcal","Price":25.0},{"Alcohol Type":"Mezcal","Brand":"Bozal Ensamble Mezcal","Price":17.0},{"Alcohol Type":"Mezcal","Brand":"Bozal Tobasiche Mezcal","Price":27.0},{"Alcohol Type":"Mezcal","Brand":"Casamigos Mezcal Joven","Price":21.0},{"Alcohol Type":"Mezcal","Brand":"Del Maguey Las Milpas","Price":23.0},{"Alcohol Type":"Mezcal","Brand":"Del Maguey Tobala","Price":41.0},{"Alcohol Type":"Mezcal","Brand":"Del Maguey VIDA","Price":15.0},{"Alcohol Type":"Mezcal","Brand":"El Silencio Mezcal Espadin","Price":11.0},{"Alcohol Type":"Mezcal","Brand":"Ilegal Mezcal Anejo","Price":25.0},{"Alcohol Type":"Mezcal","Brand":"Ilegal Mezcal Joven","Price":13.0},{"Alcohol Type":"Mezcal","Brand":"Ilegal Mezcal Reposado","Price":17.0},{"Alcohol Type":"Mezcal","Brand":"Komos Anejo Cristalino","Price":45.0},{"Alcohol Type":"Mezcal","Brand":"Komos Extra Anejo","Price":75.0},{"Alcohol Type":"Mezcal","Brand":"Komos Reposado Rosa","Price":35.0},{"Alcohol Type":"Mezcal","Brand":"Mezcal Vago Elote","Price":17.0},{"Alcohol Type":"Mezcal","Brand":"Wahaka Joven","Price":15.0},{"Alcohol Type":"Rye","Brand":"Angel's Envy Rye","Price":27.5},{"Alcohol Type":"Rye","Brand":"Basil Hayden Dark Rye","Price":15.5},{"Alcohol Type":"Rye","Brand":"Bulleit Rye 1L","Price":11.0},{"Alcohol Type":"Rye","Brand":"Buzzard's Roost Barrel Strength Rye","Price":18.5},{"Alcohol Type":"Rye","Brand":"Chicken Cock Rye","Price":28.0},{"Alcohol Type":"Rye","Brand":"Chicken Cock \"Island Rooster\" Barrel Rum Rye","Price":55.0},{"Alcohol Type":"Rye","Brand":"Elijah Craig Straight Rye","Price":21.5},{"Alcohol Type":"Rye","Brand":"George Dickel Rye","Price":11.0},{"Alcohol Type":"Rye","Brand":"Hayner Rye","Price":17.5},{"Alcohol Type":"Rye","Brand":"High West Double Rye","Price":14.5},{"Alcohol Type":"Rye","Brand":"Kentucky Owl 10yr Last Rye","Price":62.5},{"Alcohol Type":"Rye","Brand":"Masterson's Rye","Price":20.5},{"Alcohol Type":"Rye","Brand":"Michter's Rye Single Barrel","Price":17.5},{"Alcohol Type":"Rye","Brand":"Michter's 10 YEAR RYE","Price":42.5},{"Alcohol Type":"Rye","Brand":"Middle West Straight Rye Whiskey (Pumpernickel)","Price":20.5},{"Alcohol Type":"Rye","Brand":"Old Overholt Rye","Price":11.0},{"Alcohol Type":"Rye","Brand":"Redemption Rye","Price":38.5},{"Alcohol Type":"Rye","Brand":"Rittenhouse Rye","Price":11.75},{"Alcohol Type":"Rye","Brand":"Smooth Ambler Contradiction Rye","Price":14.5},{"Alcohol Type":"Rye","Brand":"Three Chord Amplify Rye","Price":17.5},{"Alcohol Type":"Rye","Brand":"Uncle Nearest Rye","Price":26.0},{"Alcohol Type":"Rye","Brand":"Whistlepig Farmstock Rye - Crop 3","Price":26.5},{"Alcohol Type":"Rye","Brand":"Whistlepig Homefield Hog Batch 2","Price":25.5},{"Alcohol Type":"Rye","Brand":"Whistlepig 6 Piggyback Rye","Price":23.0},{"Alcohol Type":"Rye","Brand":"Whistlepig 10 Rye","Price":26.5},{"Alcohol Type":"Rye","Brand":"Whistlepig 12 Straight Rye","Price":37.5},{"Alcohol Type":"Rye","Brand":"Whistlepig 15 Estate Rye","Price":60.0},{"Alcohol Type":"Rye","Brand":"Whistlepig 18","Price":61.0},{"Alcohol Type":"Rye","Brand":"Willett Family Estate Sm Batch Rye 4yr","Price":20.5},{"Alcohol Type":"Rye","Brand":"Wiseman Rye","Price":17.5},{"Alcohol Type":"Rye","Brand":"Woodford Reserve Rye","Price":14.5},{"Alcohol Type":"Whiskey","Brand":"Blue Spot 7yr Irish Whiskey","Price":29.5},{"Alcohol Type":"Whiskey","Brand":"Bushmills Irish Whiskey","Price":11.0},{"Alcohol Type":"Whiskey","Brand":"Canadian Club 1L","Price":11.0},{"Alcohol Type":"Whiskey","Brand":"Crown Royal","Price":12.5},{"Alcohol Type":"Whiskey","Brand":"Crown Royal Peach","Price":12.5},{"Alcohol Type":"Whiskey","Brand":"Jack Daniel's 1L","Price":11.0},{"Alcohol Type":"Whiskey","Brand":"Jack Daniel's Bonded","Price":13.5},{"Alcohol Type":"Whiskey","Brand":"Jack Daniel's Mash 100 proof","Price":14.5},{"Alcohol Type":"Whiskey","Brand":"Jack Daniel's American Single Malt","Price":15.5},{"Alcohol Type":"Whiskey","Brand":"Jameson 1L","Price":11.75},{"Alcohol Type":"Whiskey","Brand":"Jameson 18yr","Price":42.5},{"Alcohol Type":"Whiskey","Brand":"Jefferson's Rye Cognac Finish","Price":20.5},{"Alcohol Type":"Whiskey","Brand":"Rattle & Snap TN Whiskey","Price":12.5},{"Alcohol Type":"Whiskey","Brand":"Red Spot 15yr Irish Whiskey","Price":37.5},{"Alcohol Type":"Whiskey","Brand":"Suntory Toki Japanese Whisky","Price":12.5},{"Alcohol Type":"Whiskey","Brand":"TX Blended Whiskey","Price":13.5},{"Alcohol Type":"Whiskey","Brand":"Uncle Nearest 1856","Price":24.0},{"Alcohol Type":"Whiskey","Brand":"Uncle Nearest 1884","Price":26.0}]